[
    {
        "date":"01-01-2017",
        "close":20.68
    },
    {
        "date":"02-01-2017",
        "close":28.05
    },
    {
        "date":"03-01-2017",
        "close":30.8175
    },
    {
        "date":"04-01-2017",
        "close":33.8175
    },
    {
        "date":"05-01-2017",
        "close":40.8175
    },
    {
        "date":"06-01-2017",
        "close":38.05
    },
    {
        "date":"07-01-2017",
        "close":43.8175
    },
    {
        "date":"08-01-2017",
        "close":40.8175
    },
    {
        "date":"09-01-2017",
        "close":47.8175
    }

]
